{
  "_fv": 47,
  "_type": "tool",
  "definition": {
    "toolType": "Pickaxe",
    "renderType": 0,
    "texture": "steal_pickaxe",
    "customModelName": "Normal",
    "name": "Steal Pickaxe",
    "specialInfo": [],
    "creativeTab": {
      "value": "CUSTOM:Sad"
    },
    "harvestLevel": 5,
    "efficiency": 10.0,
    "attackSpeed": 1.0,
    "enchantability": 32,
    "damageVsEntity": 5.0,
    "usageCount": 802,
    "blocksAffected": [],
    "hasGlow": false,
    "repairItems": [
      {
        "value": "CUSTOM:StealIngot"
      }
    ],
    "immuneToFire": false,
    "stayInGridWhenCrafting": false,
    "damageOnCrafting": false
  }
}